config/__init__.py
config/const.py
config/global_settings.py
storagetest/__init__.py
storagetest/main.py
storagetest/libs/__init__.py
storagetest/libs/decorators.py
storagetest/libs/exceptions.py
storagetest/libs/sys_info.py
storagetest/libs/utils.py
storagetest/libs/customtestcase/__init__.py
storagetest/libs/customtestcase/case.py
storagetest/libs/log/__init__.py
storagetest/libs/log/log.py
storagetest/libs/multirunner/README.md
storagetest/libs/multirunner/__init__.py
storagetest/libs/multirunner/multi_runner.py
storagetest/libs/retry/__init__.py
storagetest/libs/retry/retry.py
storagetest/libs/schedule/__init__.py
storagetest/libs/schedule/schedule.py
storagetest/pkgs/__init__.py
storagetest/pkgs/base.py
storagetest/pkgs/dd/__init__.py
storagetest/pkgs/dd/dd.py
storagetest/pkgs/dd/bin/dd.exe
storagetest/pkgs/dd/bin/sdelete.exe
storagetest/pkgs/filebench/__init__.py
storagetest/pkgs/filebench/filebench.py
storagetest/pkgs/filebench/filebench_test.py
storagetest/pkgs/filebench/workloads/.cvsignore
storagetest/pkgs/filebench/workloads/Makefile
storagetest/pkgs/filebench/workloads/Makefile.am
storagetest/pkgs/filebench/workloads/Makefile.in
storagetest/pkgs/filebench/workloads/compflow_demo.f
storagetest/pkgs/filebench/workloads/copyfiles.f
storagetest/pkgs/filebench/workloads/createdelete-swing.f
storagetest/pkgs/filebench/workloads/createfiles.f
storagetest/pkgs/filebench/workloads/cvar_example.f
storagetest/pkgs/filebench/workloads/filemicro_create.f
storagetest/pkgs/filebench/workloads/filemicro_createfiles.f
storagetest/pkgs/filebench/workloads/filemicro_createrand.f
storagetest/pkgs/filebench/workloads/filemicro_delete.f
storagetest/pkgs/filebench/workloads/filemicro_rread.f
storagetest/pkgs/filebench/workloads/filemicro_rwrite.f
storagetest/pkgs/filebench/workloads/filemicro_rwritedsync.f
storagetest/pkgs/filebench/workloads/filemicro_rwritefsync.f
storagetest/pkgs/filebench/workloads/filemicro_seqread.f
storagetest-1.1.8.dist-info/LICENSE
storagetest-1.1.8.dist-info/METADATA
storagetest-1.1.8.dist-info/WHEEL
storagetest-1.1.8.dist-info/top_level.txt
storagetest-1.1.8.dist-info/RECORD
