Metadata-Version: 2.1
Name: storagetest
Version: 1.1.8
Summary: Storage Test tools/scripts.
Home-page: https://github.com/txu2k8/storage-test
Author: tao.xu
Author-email: tao.xu2008@outlook.com
License: MIT
Keywords: storagetest,filesystem,raw,cloud
Platform: UNKNOWN
Classifier: Intended Audience :: Developers
Classifier: License :: OSI Approved :: MIT License
Classifier: Natural Language :: English
Classifier: Programming Language :: Python :: 3
Requires-Python: >=3.4.0
Requires-Dist: coloredlogs (==14.0)
Requires-Dist: parameterized (==0.7.4)
Requires-Dist: prettytable (==2.0.0)
Requires-Dist: progressbar (==2.5)
Requires-Dist: xlrd (==1.2.0)
Requires-Dist: stressrunner (==1.1.9)
